flir_image_extractor_cli/__init__.py
flir_image_extractor_cli/__main__.py
flir_image_extractor_cli/dialogs.py
flir_image_extractor_cli/flir_image_extractor.py
flir_image_extractor_cli/processing.py
flir_image_extractor_cli-1.0.2.dist-info/LICENSE
flir_image_extractor_cli-1.0.2.dist-info/METADATA
flir_image_extractor_cli-1.0.2.dist-info/WHEEL
flir_image_extractor_cli-1.0.2.dist-info/entry_points.txt
flir_image_extractor_cli-1.0.2.dist-info/top_level.txt
flir_image_extractor_cli-1.0.2.dist-info/RECORD
