Metadata-Version: 2.1
Name: flir-image-extractor-cli
Version: 1.0.2
Summary: A cli-tool to get thermal information out of FLIR radiometric JPGs
Home-page: https://github.com/nationaldronesau/FlirImageExtractor
Author: National Drones
Author-email: development@nationaldrones.com
License: MIT
Platform: UNKNOWN
Classifier: Programming Language :: Python :: 3
Classifier: License :: OSI Approved :: MIT License
Classifier: Operating System :: OS Independent
Requires-Dist: numpy
Requires-Dist: pillow
Requires-Dist: matplotlib
Requires-Dist: loguru
Requires-Dist: prompt-toolkit
